CHANGELOG.md
CREDITS.html
LICENSE.txt
MANIFEST.in
README.md
joulescope.iss
pyproject.toml
setup.cfg
setup.py
joulescope_ui/CHANGELOG.md
joulescope_ui/CREDITS.html
joulescope_ui/__init__.py
joulescope_ui/__main__.py
joulescope_ui/about.py
joulescope_ui/api.py
joulescope_ui/app.py
joulescope_ui/capabilities.py
joulescope_ui/dev_signal_buffer_source.py
joulescope_ui/disk_monitor.py
joulescope_ui/error_dialog.py
joulescope_ui/error_window.py
joulescope_ui/expanding_widget.py
joulescope_ui/exporter.py
joulescope_ui/file_dialog.py
joulescope_ui/filename_formatter.py
joulescope_ui/fonts.rcc
joulescope_ui/getting_started.py
joulescope_ui/help_ui.py
joulescope_ui/intel_graphics_dialog.py
joulescope_ui/jls_source.py
joulescope_ui/jls_v1.py
joulescope_ui/jls_v2.py
joulescope_ui/jls_v2_annotations.py
joulescope_ui/json_plus.py
joulescope_ui/locale_dialog.py
joulescope_ui/logging_util.py
joulescope_ui/main.py
joulescope_ui/mem_leak_debugger.py
joulescope_ui/metadata.py
joulescope_ui/paths.py
joulescope_ui/process_monitor.py
joulescope_ui/profile.py
joulescope_ui/pubsub.py
joulescope_ui/pubsub_aggregator.py
joulescope_ui/pubsub_callable.py
joulescope_ui/pubsub_proxy.py
joulescope_ui/range_tool.py
joulescope_ui/reporter.py
joulescope_ui/resources.py
joulescope_ui/resources.rcc
joulescope_ui/safe_mode.py
joulescope_ui/sanitize.py
joulescope_ui/shift_key.py
joulescope_ui/software_update.py
joulescope_ui/source_selector.py
joulescope_ui/time_map.py
joulescope_ui/tokens.py
joulescope_ui/tooltip.py
joulescope_ui/ui_util.py
joulescope_ui/units.py
joulescope_ui/urls.py
joulescope_ui/version.py
joulescope_ui/versioned_file.py
joulescope_ui/view.py
joulescope_ui/widget_tools.py
joulescope_ui/windows.py
joulescope_ui/zip_inspector.py
joulescope_ui.egg-info/PKG-INFO
joulescope_ui.egg-info/SOURCES.txt
joulescope_ui.egg-info/dependency_links.txt
joulescope_ui.egg-info/entry_points.txt
joulescope_ui.egg-info/requires.txt
joulescope_ui.egg-info/top_level.txt
joulescope_ui/devices/__init__.py
joulescope_ui/devices/device_update.py
joulescope_ui/devices/serial_generator.py
joulescope_ui/devices/jsdrv/__init__.py
joulescope_ui/devices/jsdrv/device.py
joulescope_ui/devices/jsdrv/js110.py
