Metadata-Version: 2.4
Name: joulescope_ui
Version: 1.4.2
Summary: Joulescope™ graphical user interface
Home-page: https://www.joulescope.com
Author: Jetperch LLC
Author-email: joulescope-dev@jetperch.com
License: Apache-2.0
Project-URL: Bug Reports, https://github.com/jetperch/pyjoulescope_ui/issues
Project-URL: Funding, https://www.joulescope.com
Project-URL: Twitter, https://twitter.com/joulescope
Project-URL: Source, https://github.com/jetperch/pyjoulescope_ui/
Keywords: joulescope ui gui "user interface"
Classifier: Development Status :: 5 - Production/Stable
Classifier: Intended Audience :: Developers
Classifier: Intended Audience :: End Users/Desktop
Classifier: Intended Audience :: Science/Research
Classifier: License :: OSI Approved :: Apache Software License
Classifier: Natural Language :: English
Classifier: Operating System :: Microsoft :: Windows :: Windows 10
Classifier: Operating System :: Microsoft :: Windows :: Windows 11
Classifier: Operating System :: MacOS
Classifier: Operating System :: MacOS :: MacOS X
Classifier: Operating System :: POSIX :: Linux
Classifier: Programming Language :: Python :: 3.11
Classifier: Programming Language :: Python :: 3.12
Classifier: Programming Language :: Python :: 3.13
Classifier: Programming Language :: Python :: 3.14
Classifier: Topic :: Scientific/Engineering
Classifier: Topic :: Software Development :: Embedded Systems
Classifier: Topic :: Software Development :: Testing
Classifier: Topic :: Utilities
Requires-Python: ~=3.11
License-File: LICENSE.txt
Requires-Dist: appnope<1,>=0.1.2
Requires-Dist: fs<3,>=2.4.16
Requires-Dist: pyjoulescope_driver<2,>=1.11.0
Requires-Dist: joulescope<2,>=1.4.0
Requires-Dist: markdown<4,>=3
Requires-Dist: psutil<8,>=5
Requires-Dist: pyjls<1,>=0.16.0
Requires-Dist: pyopengl<4,>=3
Requires-Dist: pywin32>=223; platform_system == "Windows"
Requires-Dist: pyqtgraph<1,>=0.14.0
Requires-Dist: PySide6==6.10.1
Requires-Dist: PySide6-QtAds==4.5.0
Requires-Dist: python-dateutil<3,>=2.7.3
Requires-Dist: QtPy<3,>=2
Requires-Dist: requests<3,>=2
Requires-Dist: watchdog<7,>=6
Provides-Extra: dev
Requires-Dist: check-manifest; extra == "dev"
Requires-Dist: coverage; extra == "dev"
Requires-Dist: Cython; extra == "dev"
Requires-Dist: pyinstaller; extra == "dev"
Requires-Dist: wheel; extra == "dev"
Dynamic: author
Dynamic: author-email
Dynamic: classifier
Dynamic: description
Dynamic: description-content-type
Dynamic: home-page
Dynamic: keywords
Dynamic: license
Dynamic: license-file
Dynamic: project-url
Dynamic: provides-extra
Dynamic: requires-dist
Dynamic: requires-python
Dynamic: summary
